CHANGELOG.rst
MANIFEST.in
README.rst
setup.py
qifparse/__init__.py
qifparse/parser.py
qifparse/qif.py
qifparse/tests/__init__.py
qifparse/tests/file.qif
qifparse/tests/test_create.py
qifparse/tests/test_parse.py
qifparse/tests/transactions_only.qif
qifparser.egg-info/PKG-INFO
qifparser.egg-info/SOURCES.txt
qifparser.egg-info/dependency_links.txt
qifparser.egg-info/entry_points.txt
qifparser.egg-info/not-zip-safe
qifparser.egg-info/requires.txt
qifparser.egg-info/top_level.txt